odenlls/__init__.py
odenlls/odenlls.py
odenlls-0.1.0.dist-info/DESCRIPTION.rst
odenlls-0.1.0.dist-info/METADATA
odenlls-0.1.0.dist-info/RECORD
odenlls-0.1.0.dist-info/WHEEL
odenlls-0.1.0.dist-info/metadata.json
odenlls-0.1.0.dist-info/top_level.txt
