Metadata-Version: 2.0
Name: odenlls
Version: 0.1.0
Summary: Non-linear least squares fitting of chemical kinetics data using ODE simulations
Home-page: https://github.com/rnelsonchem/ODEnlls
Author: Ryan Nelson
Author-email: rnelsonchem@gmail.com
License: MIT
Keywords: non-linear fitting chemical kinetics ordinary differential equations ode
Platform: UNKNOWN
Classifier: Development Status :: 4 - Beta
Classifier: Intended Audience :: Science/Research
Classifier: License :: OSI Approved :: MIT License
Classifier: Programming Language :: Python :: 3
Requires-Dist: numpy (>=1.13.3)
Requires-Dist: scipy (>=1.0.0)
Requires-Dist: pandas (>=0.21.1)
Requires-Dist: matplotlib (>=2.1.1)
